cdoctest/__init__.py
cdoctest/__main__.py
cdoctest/c_doctest.py
cdoctest/cdoctest.py
cdoctest/cmake_api.py
cdoctest-1.4.20.dist-info/LICENSE
cdoctest-1.4.20.dist-info/METADATA
cdoctest-1.4.20.dist-info/WHEEL
cdoctest-1.4.20.dist-info/top_level.txt
cdoctest-1.4.20.dist-info/RECORD
