Metadata-Version: 2.1
Name: cdoctest
Version: 1.4.20
Summary: doctest for C/C++ which run tests by using clang-repl interaction comments.
Home-page: https://github.com/ormastes/cdoctest
Author: Yoon, Jonghyun
Author-email: ormastes@gmail.com
Classifier: Intended Audience :: Developers
Classifier: License :: OSI Approved :: Apache Software License
Classifier: Programming Language :: Python :: 3
License-File: LICENSE
Requires-Dist: clang
Requires-Dist: clang_repl_kernel>=1.4.18
Requires-Dist: ipykernel
Requires-Dist: libclang
Requires-Dist: ordered_set
Requires-Dist: cmake_file_api
